.coveragerc
.gitignore
.travis.yml
CHANGES.txt
MANIFEST.in
README.rst
base.cfg
bootstrap.py
buildout.cfg
endpoints.csv
setup.py
test-plone4.x.cfg
test-release.cfg
travis.cfg
collective/__init__.py
collective.oembed.egg-info/PKG-INFO
collective.oembed.egg-info/SOURCES.txt
collective.oembed.egg-info/dependency_links.txt
collective.oembed.egg-info/entry_points.txt
collective.oembed.egg-info/namespace_packages.txt
collective.oembed.egg-info/not-zip-safe
collective.oembed.egg-info/requires.txt
collective.oembed.egg-info/top_level.txt
collective/oembed/__init__.py
collective/oembed/configure.zcml
collective/oembed/consumer.py
collective/oembed/embedly.py
collective/oembed/endpoints.py
collective/oembed/endpoints_test_view.pt
collective/oembed/endpoints_test_view.zcml
collective/oembed/i18n.py
collective/oembed/interfaces.py
collective/oembed/jquery.oembed.js
collective/oembed/link_view.pt
collective/oembed/link_view.py
collective/oembed/provider.py
collective/oembed/provider_dexterity.py
collective/oembed/provider_xml.pt
collective/oembed/upgrades.py
collective/oembed/upgrades.zcml
collective/oembed/viewlet-discovery.pt
collective/oembed/viewlet-jquery-oembed.pt
collective/oembed/viewlet.py
collective/oembed/vocabulary.py
collective/oembed/api2embed/__init__.py
collective/oembed/api2embed/structure.py
collective/oembed/api2embed/twitteruser.py
collective/oembed/profiles/default/browserlayer.xml
collective/oembed/profiles/default/jsregistry.xml
collective/oembed/profiles/default/metadata.xml
collective/oembed/profiles/default/registry.xml
collective/oembed/profiles/default/tinymce.xml
collective/oembed/profiles/default/types/Link.xml
collective/oembed/tests/__init__.py
collective/oembed/tests/base.py
collective/oembed/tests/layer.py
collective/oembed/tests/test_consumer.py
collective/oembed/tests/test_endpoints.py
collective/oembed/tests/test_provider.py
collective/oembed/tests/test_twitteruser.py
collective/oembed/tests/test_urlendpoints.py
collective/oembed/tests/test_viewlet_discovery.py
collective/oembed/tests/test_viewlet_jquery_oembed.py
collective/oembed/tests/utils.py
collective/oembed/tile/__init__.py
collective/oembed/tile/configure.zcml
collective/oembed/tile/example.pt
collective/oembed/tile/example.py
collective/oembed/tile/example.zcml
collective/oembed/tile/oembedtile.pt
